Workbook

Sheet Start
A1: Stundensatz & Steuerrücklage
A2: Kalkulationsmappe für Einzelunternehmer und Solo-Selbstständige
A4: SO GEHT'S
A5: Schritt 1 | B5: Blatt «Eingaben» ausfüllen. Nur die gelben Felder — alles andere rechnet sich selbst.
A6: Schritt 2 | B6: Blatt «Stundensatz» lesen. Dort steht, was du mindestens verlangen musst.
A7: Schritt 3 | B7: Auf «Steuerrücklage» Monat für Monat deine echten Einnahmen eintragen.
A9: DIE BLÄTTER
A10: Eingaben | B10: Deine Zahlen. Das einzige Blatt, das du zwingend ausfüllen musst.
A11: Stundensatz | B11: Mindestsatz, Tagessatz, Abgleich mit deinem heutigen Satz, Sensitivitätstabelle.
A12: Steuerrücklage | B12: Wie viel du monatlich für Einkommen- und Umsatzsteuer zurücklegen solltest.
A13: Liquidität | B13: Kontostand über 12 Monate. Engpassmonate werden rot.
A14: Auswertung | B14: Kostenstruktur und Kontostandsverlauf als Diagramm.
A15: Hinweise | B15: Haftungsausschluss und Nutzungsbedingungen. Bitte einmal lesen.
A17: FARBEN
A18: Gelb | B18: Hier trägst du etwas ein.
A19: Schwarz | B19: Rechnet sich automatisch. Bitte nicht überschreiben.
A20: Grün | B20: Holt den Wert von einem anderen Blatt.
A22: BEISPIELWERTE
B23: Die Mappe ist mit realistischen Beispielzahlen gefüllt, damit du sofort siehst, wie sie arbeitet. Überschreib sie mit deinen eigenen. Die Einnahmen auf dem Blatt «Steuerrücklage» sind ebenfalls nur ein Beispiel.
A25: WICHTIG
B26: Diese Mappe ist ein Kalkulationswerkzeug, kein steuerlicher Nachweis und keine Steuerberatung. Sie rechnet mit einem pauschalen Steuersatz und bildet deine persönliche Progression nicht exakt ab. Details auf dem Blatt «Hinweise».

Sheet Eingaben
A1: Eingaben
A2: Nur die gelben Felder ausfüllen. Alles andere rechnet sich selbst.
A4: Lebenshaltung — pro Monat, nach Steuern
A5: Gewünschtes Netto | B5: 2500 | D5: Was privat übrig bleiben soll
A6: Krankenversicherung | B6: 600 | D6: Als Selbstständiger zahlst du sie selbst
A7: Altersvorsorge | B7: 200 | D7: Rürup, ETF-Sparplan, Versorgungswerk …
A8: Summe Lebenshaltung | B8: =SUM(B5:B7)
A10: Betriebskosten — pro Monat, ohne Umsatzsteuer
A11: Büro / Miete / Arbeitszimmer | B11: 150
A12: Software & Abos | B12: 60
A13: Versicherungen (betrieblich) | B13: 80
A14: Fahrzeug & Fahrtkosten | B14: 120
A15: Steuerberater / Buchhaltung | B15: 90
A16: Fortbildung | B16: 40
A17: Werkzeug, Material, Sonstiges | B17: 60
A18: Summe Betriebskosten | B18: =SUM(B11:B17)
A20: Steuern
A21: Steuersatz auf den Gewinn | B21: 0.3 | D21: Grobe Annahme. Bei kleineren Gewinnen eher 20–30 %
A22: Umsatzsteuersatz | B22: 0.19 | D22: 19 % Regelsatz, 7 % ermäßigt
A23: Kleinunternehmer nach § 19 UStG | B23: Nein | D23: Bei «Ja» wird keine Umsatzsteuer berechnet
A25: Arbeitszeit
A26: Wochenstunden | B26: 40 | D26: Was du tatsächlich arbeitest
A27: Urlaubstage pro Jahr | B27: 30
A28: Krankheitstage pro Jahr | B28: 8 | D28: Lieber realistisch als optimistisch ansetzen
A29: Feiertage pro Jahr | B29: 10 | D29: Bundesland-abhängig, meist 9–13
A30: Produktivquote | B30: 0.6 | D30: Anteil deiner Zeit, den du abrechnen kannst
A31: Gewinnaufschlag / Risikopuffer | B31: 0.1 | D31: Rücklage für Investitionen und schlechte Monate
A33: Abgleich & Startwerte
A34: Aktueller Stundensatz | B34: 60 | D34: Was du heute verlangst — für den Vergleich
A35: Startkontostand | B35: 3000 | D35: Für den Liquiditätsplan
A37: Warum die Produktivquote alles entscheidet
A38: Wer 40 Stunden pro Woche im Betrieb ist, rechnet davon selten mehr als 24 ab — der Rest geht für Angebote, Buchhaltung, Fahrten, Akquise und Leerlauf drauf. 100 % gibt es nicht. Realistisch sind 50–70 %. Wie stark dieser eine Wert durchschlägt, siehst du in der Tabelle unten auf dem Blatt «Stundensatz».

Sheet Stundensatz
A1: Dein Stundensatz
A2: Ergebnis aus dem Blatt «Eingaben». Hier musst du nichts eintragen.
A4: Was du im Jahr erwirtschaften musst
A5: Lebenshaltung pro Jahr | B5: =Eingaben!B8*12
A6: Nötiger Gewinn vor Steuern | B6: =B5/(1-Eingaben!B21) | D6: Weil auf den Gewinn noch Steuern anfallen
A7: Betriebskosten pro Jahr | B7: =Eingaben!B18*12
A8: Zwischensumme | B8: =B6+B7
A9: Gewinnaufschlag / Puffer | B9: =B8*Eingaben!B31
A10: Nötiger Jahresumsatz (netto) | B10: =B8+B9
A12: Wie viel Zeit du wirklich abrechnen kannst
A13: Arbeitstage im Jahr | B13: =260-Eingaben!B27-Eingaben!B28-Eingaben!B29 | D13: 260 Werktage minus Urlaub, Krankheit, Feiertage
A14: Stunden pro Tag | B14: =Eingaben!B26/5
A15: Anwesenheitsstunden im Jahr | B15: =B13*B14
A16: Davon abrechenbar | B16: =B15*Eingaben!B30
A18: Ergebnis
A19: MINDEST-STUNDENSATZ (netto) | B19: =IF(B16>0,B10/B16,0) | D19: Darunter arbeitest du unter deinen Kosten
A20: Tagessatz | B20: =B19*B14
A21: Stundensatz brutto (mit Umsatzsteuer) | B21: =IF(Eingaben!B23="Ja",B19,B19*(1+Eingaben!B22)) | D21: Das steht auf der Rechnung
A23: Abgleich mit deinem heutigen Satz
A24: Aktueller Stundensatz | B24: =Eingaben!B34
A25: Differenz je Stunde | B25: =B24-B19
A26: Differenz im Jahr | B26: =B25*B16
A27: Bewertung | B27: =IF(B24>=B19,"Dein Satz trägt.",IF(B24>=B19*0.85,"Knapp kalkuliert — ein Auftragsloch reißt dich ins Minus.","Unterdeckung — du arbeitest die Differenz unbezahlt ab."))
A29: Was passiert, wenn sich die Produktivquote ändert
A30: Produktivquote | B30: Abrechenbare Stunden | C30: Nötiger Stundensatz | D30: Tagessatz
A31: 0.4 | B31: =$B$15*A31 | C31: =IF(B31>0,$B$10/B31,0) | D31: =C31*$B$14
A32: 0.45 | B32: =$B$15*A32 | C32: =IF(B32>0,$B$10/B32,0) | D32: =C32*$B$14
A33: 0.5 | B33: =$B$15*A33 | C33: =IF(B33>0,$B$10/B33,0) | D33: =C33*$B$14
A34: 0.55 | B34: =$B$15*A34 | C34: =IF(B34>0,$B$10/B34,0) | D34: =C34*$B$14
A35: 0.6 | B35: =$B$15*A35 | C35: =IF(B35>0,$B$10/B35,0) | D35: =C35*$B$14
A36: 0.65 | B36: =$B$15*A36 | C36: =IF(B36>0,$B$10/B36,0) | D36: =C36*$B$14
A37: 0.7 | B37: =$B$15*A37 | C37: =IF(B37>0,$B$10/B37,0) | D37: =C37*$B$14
A38: 0.75 | B38: =$B$15*A38 | C38: =IF(B38>0,$B$10/B38,0) | D38: =C38*$B$14
A39: 0.8 | B39: =$B$15*A39 | C39: =IF(B39>0,$B$10/B39,0) | D39: =C39*$B$14
A40: 0.85 | B40: =$B$15*A40 | C40: =IF(B40>0,$B$10/B40,0) | D40: =C40*$B$14

Sheet Steuerrücklage
A1: Steuerrücklage
A2: Trag jeden Monat deine echten Einnahmen ein. Der Rest rechnet sich.
A3: Die Einnahmen unten sind Beispielwerte. Bitte durch deine eigenen Zahlen ersetzen.
A4: Monat | B4: Einnahmen netto | C4: Betriebsausgaben | D4: Gewinn | E4: Rücklage Einkommensteuer | F4: Rücklage Umsatzsteuer | G4: Rücklage gesamt | H4: Kumuliert
A5: Januar | B5: 5700 | C5: =Eingaben!$B$18 | D5: =B5-C5 | E5: =MAX(D5,0)*Eingaben!$B$21 | F5: =IF(Eingaben!$B$23="Ja",0,B5*Eingaben!$B$22) | G5: =E5+F5 | H5: =G5
A6: Februar | B6: 5700 | C6: =Eingaben!$B$18 | D6: =B6-C6 | E6: =MAX(D6,0)*Eingaben!$B$21 | F6: =IF(Eingaben!$B$23="Ja",0,B6*Eingaben!$B$22) | G6: =E6+F6 | H6: =H5+G6
A7: März | B7: 5700 | C7: =Eingaben!$B$18 | D7: =B7-C7 | E7: =MAX(D7,0)*Eingaben!$B$21 | F7: =IF(Eingaben!$B$23="Ja",0,B7*Eingaben!$B$22) | G7: =E7+F7 | H7: =H6+G7
A8: April | B8: 5700 | C8: =Eingaben!$B$18 | D8: =B8-C8 | E8: =MAX(D8,0)*Eingaben!$B$21 | F8: =IF(Eingaben!$B$23="Ja",0,B8*Eingaben!$B$22) | G8: =E8+F8 | H8: =H7+G8
A9: Mai | B9: 5700 | C9: =Eingaben!$B$18 | D9: =B9-C9 | E9: =MAX(D9,0)*Eingaben!$B$21 | F9: =IF(Eingaben!$B$23="Ja",0,B9*Eingaben!$B$22) | G9: =E9+F9 | H9: =H8+G9
A10: Juni | B10: 5700 | C10: =Eingaben!$B$18 | D10: =B10-C10 | E10: =MAX(D10,0)*Eingaben!$B$21 | F10: =IF(Eingaben!$B$23="Ja",0,B10*Eingaben!$B$22) | G10: =E10+F10 | H10: =H9+G10
A11: Juli | B11: 5700 | C11: =Eingaben!$B$18 | D11: =B11-C11 | E11: =MAX(D11,0)*Eingaben!$B$21 | F11: =IF(Eingaben!$B$23="Ja",0,B11*Eingaben!$B$22) | G11: =E11+F11 | H11: =H10+G11
A12: August | B12: 5700 | C12: =Eingaben!$B$18 | D12: =B12-C12 | E12: =MAX(D12,0)*Eingaben!$B$21 | F12: =IF(Eingaben!$B$23="Ja",0,B12*Eingaben!$B$22) | G12: =E12+F12 | H12: =H11+G12
A13: September | B13: 5700 | C13: =Eingaben!$B$18 | D13: =B13-C13 | E13: =MAX(D13,0)*Eingaben!$B$21 | F13: =IF(Eingaben!$B$23="Ja",0,B13*Eingaben!$B$22) | G13: =E13+F13 | H13: =H12+G13
A14: Oktober | B14: 5700 | C14: =Eingaben!$B$18 | D14: =B14-C14 | E14: =MAX(D14,0)*Eingaben!$B$21 | F14: =IF(Eingaben!$B$23="Ja",0,B14*Eingaben!$B$22) | G14: =E14+F14 | H14: =H13+G14
A15: November | B15: 5700 | C15: =Eingaben!$B$18 | D15: =B15-C15 | E15: =MAX(D15,0)*Eingaben!$B$21 | F15: =IF(Eingaben!$B$23="Ja",0,B15*Eingaben!$B$22) | G15: =E15+F15 | H15: =H14+G15
A16: Dezember | B16: 5700 | C16: =Eingaben!$B$18 | D16: =B16-C16 | E16: =MAX(D16,0)*Eingaben!$B$21 | F16: =IF(Eingaben!$B$23="Ja",0,B16*Eingaben!$B$22) | G16: =E16+F16 | H16: =H15+G16
A17: Summe | B17: =SUM(B5:B16) | D17: =SUM(D5:D16) | E17: =SUM(E5:E16) | F17: =SUM(F5:F16) | G17: =SUM(G5:G16)
A19: Abgleich mit deinem Rücklagenkonto
A20: Soll-Stand Rücklage | B20: =H16 | D20: Was zurückgelegt sein müsste
A21: Ist-Stand auf dem Konto | B21: 0 | D21: Was tatsächlich da liegt
A22: Differenz | B22: =B21-B20
A23: Status | B23: =IF(B21>=B20,"Rücklage reicht.","Es fehlen "&TEXT(B20-B21,"#,##0")&" € auf dem Rücklagenkonto.")

Sheet Liquidität
A1: Liquiditätsplan
A2: Zeigt, in welchem Monat es eng wird — bevor es eng wird.
A3: Startkontostand | B3: =Eingaben!B35
A5: Monat | B5: Einnahmen brutto | C5: Betriebsausgaben | D5: Privatentnahme | E5: Steuerrücklage | F5: Saldo | G5: Kontostand
A6: Januar | B6: =IF(Eingaben!$B$23="Ja",'Steuerrücklage'!B5,'Steuerrücklage'!B5*(1+Eingaben!$B$22)) | C6: ='Steuerrücklage'!C5 | D6: =Eingaben!$B$8 | E6: ='Steuerrücklage'!G5 | F6: =B6-C6-D6-E6 | G6: =$B$3+F6
A7: Februar | B7: =IF(Eingaben!$B$23="Ja",'Steuerrücklage'!B6,'Steuerrücklage'!B6*(1+Eingaben!$B$22)) | C7: ='Steuerrücklage'!C6 | D7: =Eingaben!$B$8 | E7: ='Steuerrücklage'!G6 | F7: =B7-C7-D7-E7 | G7: =G6+F7
A8: März | B8: =IF(Eingaben!$B$23="Ja",'Steuerrücklage'!B7,'Steuerrücklage'!B7*(1+Eingaben!$B$22)) | C8: ='Steuerrücklage'!C7 | D8: =Eingaben!$B$8 | E8: ='Steuerrücklage'!G7 | F8: =B8-C8-D8-E8 | G8: =G7+F8
A9: April | B9: =IF(Eingaben!$B$23="Ja",'Steuerrücklage'!B8,'Steuerrücklage'!B8*(1+Eingaben!$B$22)) | C9: ='Steuerrücklage'!C8 | D9: =Eingaben!$B$8 | E9: ='Steuerrücklage'!G8 | F9: =B9-C9-D9-E9 | G9: =G8+F9
A10: Mai | B10: =IF(Eingaben!$B$23="Ja",'Steuerrücklage'!B9,'Steuerrücklage'!B9*(1+Eingaben!$B$22)) | C10: ='Steuerrücklage'!C9 | D10: =Eingaben!$B$8 | E10: ='Steuerrücklage'!G9 | F10: =B10-C10-D10-E10 | G10: =G9+F10
A11: Juni | B11: =IF(Eingaben!$B$23="Ja",'Steuerrücklage'!B10,'Steuerrücklage'!B10*(1+Eingaben!$B$22)) | C11: ='Steuerrücklage'!C10 | D11: =Eingaben!$B$8 | E11: ='Steuerrücklage'!G10 | F11: =B11-C11-D11-E11 | G11: =G10+F11
A12: Juli | B12: =IF(Eingaben!$B$23="Ja",'Steuerrücklage'!B11,'Steuerrücklage'!B11*(1+Eingaben!$B$22)) | C12: ='Steuerrücklage'!C11 | D12: =Eingaben!$B$8 | E12: ='Steuerrücklage'!G11 | F12: =B12-C12-D12-E12 | G12: =G11+F12
A13: August | B13: =IF(Eingaben!$B$23="Ja",'Steuerrücklage'!B12,'Steuerrücklage'!B12*(1+Eingaben!$B$22)) | C13: ='Steuerrücklage'!C12 | D13: =Eingaben!$B$8 | E13: ='Steuerrücklage'!G12 | F13: =B13-C13-D13-E13 | G13: =G12+F13
A14: September | B14: =IF(Eingaben!$B$23="Ja",'Steuerrücklage'!B13,'Steuerrücklage'!B13*(1+Eingaben!$B$22)) | C14: ='Steuerrücklage'!C13 | D14: =Eingaben!$B$8 | E14: ='Steuerrücklage'!G13 | F14: =B14-C14-D14-E14 | G14: =G13+F14
A15: Oktober | B15: =IF(Eingaben!$B$23="Ja",'Steuerrücklage'!B14,'Steuerrücklage'!B14*(1+Eingaben!$B$22)) | C15: ='Steuerrücklage'!C14 | D15: =Eingaben!$B$8 | E15: ='Steuerrücklage'!G14 | F15: =B15-C15-D15-E15 | G15: =G14+F15
A16: November | B16: =IF(Eingaben!$B$23="Ja",'Steuerrücklage'!B15,'Steuerrücklage'!B15*(1+Eingaben!$B$22)) | C16: ='Steuerrücklage'!C15 | D16: =Eingaben!$B$8 | E16: ='Steuerrücklage'!G15 | F16: =B16-C16-D16-E16 | G16: =G15+F16
A17: Dezember | B17: =IF(Eingaben!$B$23="Ja",'Steuerrücklage'!B16,'Steuerrücklage'!B16*(1+Eingaben!$B$22)) | C17: ='Steuerrücklage'!C16 | D17: =Eingaben!$B$8 | E17: ='Steuerrücklage'!G16 | F17: =B17-C17-D17-E17 | G17: =G16+F17
A19: Rot heißt: Das Konto ist rechnerisch leer. Einnahmen und Betriebsausgaben kommen vom Blatt «Steuerrücklage», die Privatentnahme von «Eingaben». Die Einnahmen sind hier brutto, weil die Umsatzsteuer erst tatsächlich auf dem Konto liegt, bevor sie ans Finanzamt geht.

Sheet Auswertung
A1: Auswertung
A2: Aktualisiert sich mit deinen Eingaben.

Sheet Hinweise
A1: Hinweise
A2: Bitte einmal lesen.
A4: Keine Steuerberatung
A5: Diese Arbeitsmappe ist ein Kalkulations- und Planungswerkzeug. Sie ersetzt keine Steuerberatung und stellt keine Rechtsberatung dar. Sie rechnet mit einem pauschalen Steuersatz und bildet weder deine persönliche Einkommensteuerprogression noch Gewerbesteuer, Vorsorgeaufwendungen, Freibeträge oder Sonderfälle exakt ab. Verbindliche Zahlen bekommst du von deinem Steuerberater.
A7: Vereinfachungen
A8: Die Umsatzsteuer-Rücklage rechnet ohne Vorsteuerabzug — die tatsächlich abzuführende Umsatzsteuer ist daher meist etwas niedriger als hier angezeigt. Das ist bewusst so: Lieber zu viel zurückgelegt als zu wenig.
A10: Kein steuerlicher Nachweis
A11: Diese Datei ist ausdrücklich kein Kassenbuch, kein Fahrtenbuch und keine Buchführung im Sinne der GoBD. Eine Tabellenkalkulation erfüllt die Anforderung der Unveränderbarkeit nicht und wird als Aufzeichnungsnachweis vom Finanzamt in der Regel nicht anerkannt. Nutze sie zum Planen, nicht zum Nachweisen.
A13: Für wen sie gedacht ist
A14: Für Einzelunternehmer, Freiberufler und Solo-Selbstständige ohne Angestellte. Betriebe mit Mitarbeitern brauchen eine andere Kalkulation, weil dort Lohnkosten, Lohnnebenkosten und Gemeinkostenzuschläge hinzukommen.
A16: Nutzungsbedingungen
A17: Für die eigene betriebliche und private Nutzung. Weitergabe, Weiterverkauf und Veröffentlichung der Datei sind nicht gestattet.
... A20: Die Nutzung erfolgt auf eigene Verantwortung. Für Entscheidungen, die auf Grundlage der Ergebnisse getroffen werden, wird keine Haftung übernommen.
